configs/__init__.py
configs/main.py
CONFIGS_dw9ga8fguawfvzauuwgzuh-0.0.1.dist-info/METADATA
CONFIGS_dw9ga8fguawfvzauuwgzuh-0.0.1.dist-info/WHEEL
CONFIGS_dw9ga8fguawfvzauuwgzuh-0.0.1.dist-info/top_level.txt
CONFIGS_dw9ga8fguawfvzauuwgzuh-0.0.1.dist-info/RECORD
