Metadata-Version: 2.1
Name: CONFIGS-dw9ga8fguawfvzauuwgzuh
Version: 0.0.1
Summary: A python package to make configs easier!
Home-page: UNKNOWN
Author: tntgamer685347
Author-email: gamer@fampl.de
License: UNKNOWN
Platform: UNKNOWN
Classifier: Development Status :: 1 - Planning
Classifier: Intended Audience :: Developers
Classifier: Programming Language :: Python :: 3
Classifier: Operating System :: Unix
Classifier: Operating System :: MacOS :: MacOS X
Classifier: Operating System :: Microsoft :: Windows
